dsbox/__init__.py
dsbox/datapreprocessing/__init__.py
dsbox/datapreprocessing/profiler/__init__.py
dsbox/datapreprocessing/profiler/data_profile.py
dsbox/datapreprocessing/profiler/feature_compute_hih.py
dsbox/datapreprocessing/profiler/feature_compute_lfh.py
dsbox/datapreprocessing/profiler/helper_funcs.py
dsbox_dataprofiling-0.3.0.dist-info/DESCRIPTION.rst
dsbox_dataprofiling-0.3.0.dist-info/METADATA
dsbox_dataprofiling-0.3.0.dist-info/RECORD
dsbox_dataprofiling-0.3.0.dist-info/WHEEL
dsbox_dataprofiling-0.3.0.dist-info/entry_points.txt
dsbox_dataprofiling-0.3.0.dist-info/metadata.json
dsbox_dataprofiling-0.3.0.dist-info/top_level.txt
