Metadata-Version: 2.0
Name: dsbox-dataprofiling
Version: 0.3.0
Summary: DSBox data profiling  tools
Home-page: https://github.com/usc-isi-i2/dsbox-cleaning.git
Author: Ke-Thia Yao
Author-email: kyao@isi.edu
License: MIT
Platform: UNKNOWN
Requires-Python: >=3.5
Requires-Dist: numpy (>=1.11.1)
Requires-Dist: pandas (>=0.20.1)
Requires-Dist: langdetect (>=1.0.7)
